MANIFEST.in
README.md
setup.py
cnilsimsa/VERSION
cnilsimsa/__init__.py
cnilsimsa/_nilsimsa.c
cnilsimsa.egg-info/PKG-INFO
cnilsimsa.egg-info/SOURCES.txt
cnilsimsa.egg-info/dependency_links.txt
cnilsimsa.egg-info/top_level.txt