Metadata-Version: 1.1
Name: cnilsimsa
Version: 0.1.0
Summary: A C implementation of Nilsimsa for Python.
Home-page: http://github.com/lukearno/cnilsimsa
Author: Luke Arno
Author-email: luke.arno@gmail.com
License: GPL2+
Platform: UNKNOWN
Classifier: Development Status :: 3 - Alpha
Classifier: Intended Audience :: Developers
Classifier: License :: OSI Approved :: GNU General Public License v2 or later (GPLv2+)
Classifier: Natural Language :: English
Classifier: Operating System :: OS Independent
Classifier: Programming Language :: Python
Classifier: Programming Language :: C
Classifier: Topic :: Software Development :: Libraries
Classifier: Topic :: Utilities
